README.md
setup.py
IntelliType/__init__.py
IntelliType/storyboard.py
IntelliType/storyvalues.py
IntelliType.egg-info/PKG-INFO
IntelliType.egg-info/SOURCES.txt
IntelliType.egg-info/dependency_links.txt
IntelliType.egg-info/entry_points.txt
IntelliType.egg-info/requires.txt
IntelliType.egg-info/top_level.txt