Metadata-Version: 2.1
Name: IntelliType
Version: 0.4.1
Summary: The goal of IntelliType is to help you automate text-based processes
Home-page: https://github.com/pmqtt/IntelliType
Author: michael burzan
Author-email: 
License: Apache 2
Platform: UNKNOWN
